manolyalogger/__init__.py
manolyalogger/loggerobj.py
manolyalogger-0.1.dist-info/METADATA
manolyalogger-0.1.dist-info/WHEEL
manolyalogger-0.1.dist-info/top_level.txt
manolyalogger-0.1.dist-info/RECORD
